{"name":"Alejandro Hurtado","tagline":"A web developer. Testing github pages as personal site.","body":"### What I'm doing\r\n\r\nTesting how to deploy Symfony2 application  to the [Openshift](https://www.openshift.com/) of RedHat and working with [Cloud9](https://c9.io/).\r\n\r\nEven when there some project for deploy Symonfy 2 (see [boekkooi](https://github.com/boekkooi/openshift-diy-symfony) or [eschabell](https://github.com/eschabell/openshift-symfony) ) I do it on my own way.\r\n\r\nThe result in [testa ](http://testa-awebzone.rhcloud.com/app.php)","google":"","note":"Don't delete this file! It's used internally to help with page regeneration."}